IntrinsicTime/__init__.py
IntrinsicTime/dcos_core/__init__.py
IntrinsicTime/dcos_core/dcos_core.py
IntrinsicTime/dcos_fractal/__init__.py
IntrinsicTime/dcos_fractal/dcos_fractal.py
IntrinsicTime/dcos_fractal/dcos_tests.py
IntrinsicTime/dcos_plot/__init__.py
IntrinsicTime/dcos_plot/dcos_plot.py
intrinsictime-0.1.3.dist-info/licenses/LICENSE
intrinsictime-0.1.3.dist-info/METADATA
intrinsictime-0.1.3.dist-info/WHEEL
intrinsictime-0.1.3.dist-info/top_level.txt
intrinsictime-0.1.3.dist-info/RECORD
