Metadata-Version: 2.4
Name: IntrinsicTime
Version: 0.1.3
Summary: Utilities for intrinsic time decomposition and fractal event analysis
Author-email: Tom Houweling <thomas.houweling@gmail.com>
License: MIT License
Requires-Python: >=3.9
License-File: LICENSE
Requires-Dist: numpy
Requires-Dist: pandas
Requires-Dist: scipy
Requires-Dist: plotly
Dynamic: license-file
